{
  "basics": {
    "name": "Demetrio Urqudi",
    "label": "Software Developer",
    "picture": "",
    "email": "info@dmtrio.me",
    "phone": "(915) 740-1365",
    "website": "http://dmtrio.me",
    "summary": "",
    "location": {
      "address": "1508 Soutport",
      "postalCode": "78704",
      "city": "San Francisco",
      "countryCode": "US",
      "region": "California"
    },
    "profiles": [{
      "network": "Github",
      "username": "dmtrio",
      "url": "https://github.com/dmtrio"
    }]
  },
  "work": [{
    "company": "Cognizant",
    "position": "Software Developer",
    "website": "http://cognizant.com",
    "startDate": "2018-01-01",
    "endDate": "",
    "summary": "Engineer in a Spotify-like squads/bands system. Conducted code reviews, coordinated releases, enforced standards",
    "highlights": [
      "Developed and packaged node-module for a customer facing chatbot",
      "Delivered new experiences that increased that increased information density and customer conversion on page view",
      "Elevated code quality by starting a conversation on standards and implementing linting",
      "Created a new shopping experience from the ground for customers to purchase related items together"
    ]
  }],
  "volunteer": [{
    "organization": "Urban Trails",
    "position": "Software Developer",
    "website": "urbantrails.dmtrio.me",
    "startDate": "",
    "endDate": "",
    "summary": "Mobile navigation app that enables cyclists in Austin to find bike amenities and submit reports.",
    "highlights": [
      "Led a mobile first design and architecture by implementing progressive web app best practices",
      "Modeled an intuitive reactive Vue interface that kept track of open SPA components through the Vuex store",
      "Implemented device responsive style scaling with Google material design guidelines"
    ]
  },
  {
    "organization": "Concreet Cal",
    "position": "Software Developer",
    "website": "",
    "startDate": "",
    "endDate": "",
    "summary": "Event scheduling app that finds available times across all invited users",
    "highlights": [
      "Integrated Passport with Google Authentication passing down access tokens for front-end API calls",
      "Queried Google Cal API’s for data of multiple offline users simultaneously",
      "Paired a React front-end with React Big Calendar module that dynamically rendered Google data"
    ]
  }
  ],
  "education": [{
    "institution": "University of Texas at Austin",
    "area": "Architecture",
    "studyType": "Bachelor",
    "startDate": "2007-08-20",
    "endDate": "2012-05-15",
    "gpa": "4.0",
    "courses": [
    ]
  },
  {
    "institution": "Hack Reactor",
    "area": "Advanced Software Engineering",
    "studyType": "Immersive Program",
    "endDate": "2017-07-30",
    "courses": [
    ]
  }],
  "awards": [{
    "title": "Award",
    "date": "2014-11-01",
    "awarder": "Company",
    "summary": "There is no spoon."
  }],
  "publications": [{
    "name": "Publication",
    "publisher": "Company",
    "releaseDate": "2014-10-01",
    "website": "http://publication.com",
    "summary": "Description..."
  }],
  "skills": [{
    "name": "Frontend Web Development",
    "level": "Master",
    "keywords": [
      "Javascript",
      "React",
      "Redux",
      "Vue",
      "Vuex",
      "jQuery",
      "Mustache",
      "HTML5",
      "CSS3",
      "Sass",
      "Angular",
      "LeafletJS"
    ]
  },
  {
    "name": "Backend Web Development",
    "level": "Master",
    "keywords": [
      "Node",
      "NextJs",
      "Express",
      "Hapi",
      "Passport",
      "Google API",
      "Java",
      "MongoDB",
      "MySQL"  
    ]
  }],
  "languages": [{
    "language": "English",
    "fluency": "Native speaker"
  },
  {
    "language": "Spanish",
    "fluency": "Native speaker"
  }],
  "interests": [{
    "name": "Wildlife",
    "keywords": [
      "Ferrets",
      "Unicorns"
    ]
  }],
  "references": [{
    "name": "Jane Doe",
    "reference": "Reference..."
  }]
}